mcwrapper/__init__.py
mcwrapper/exceptions.py
mcwrapper/hypixel.py
mcwrapper/skin.py
mcwrapper-1.38.dist-info/LICENSE
mcwrapper-1.38.dist-info/METADATA
mcwrapper-1.38.dist-info/WHEEL
mcwrapper-1.38.dist-info/top_level.txt
mcwrapper-1.38.dist-info/RECORD
