Metadata-Version: 2.1
Name: mcwrapper
Version: 1.38
Summary: A Minecraft API Wrapper
Home-page: https://github.com/ThePotatoPowers/mcapiwrapper
Author: Zidane Karim
Author-email: zkarim7676@gmail.com
License: MIT
Project-URL: Bug Tracker, https://github.com/ThePotatoPowers/mcapiwrapper/issues
Platform: UNKNOWN
Classifier: Programming Language :: Python :: 3
Classifier: License :: OSI Approved :: MIT License
Classifier: Operating System :: OS Independent
Requires-Python: >=3.7
Requires-Dist: requests
